tessy/__init__.py
tessy/_tessy.py
tessy-0.5.2.dist-info/METADATA
tessy-0.5.2.dist-info/WHEEL
tessy-0.5.2.dist-info/top_level.txt
tessy-0.5.2.dist-info/RECORD
