Metadata-Version: 2.1
Name: tessy
Version: 0.5.2
Summary: A Python wrapper for Tesseract-OCR.
Home-page: https://github.com/k4rian/tessy
Author: K4rian
Author-email: contact@k4rian.com
License: MIT
Keywords: python tesseract ocr
Classifier: Development Status :: 4 - Beta
Classifier: License :: OSI Approved :: MIT License
Classifier: Operating System :: Microsoft :: Windows
Classifier: Operating System :: POSIX :: Linux
Classifier: Operating System :: MacOS
Classifier: Programming Language :: Python
Classifier: Programming Language :: Python :: 3.12
Classifier: Topic :: Utilities
